{"volumes": [687, 0, 0, 1174, 749, 0, 1901, 490, 1864, 620, 459, 685, 0, 1108, 0, 1214, 1555, 310, 0, 963, 0, 597, 396, 0, 536], "conflicts": [[0, 1], [0, 2], [0, 5], [0, 14], [0, 23], [0, 24], [1, 2], [1, 4], [1, 7], [1, 10], [1, 11], [1, 12], [1, 14], [1, 15], [1, 16], [1, 18], [1, 20], [1, 24], [2, 3], [2, 5], [2, 9], [2, 12], [2, 13], [2, 15], [2, 16], [2, 17], [2, 18], [2, 19], [2, 20], [2, 23], [3, 12], [3, 14], [3, 20], [4, 14], [4, 20], [4, 22], [4, 23], [4, 24], [5, 6], [5, 7], [5, 8], [5, 11], [5, 14], [5, 15], [5, 16], [5, 17], [5, 19], [5, 23], [6, 14], [6, 20], [6, 23], [7, 18], [7, 20], [8, 12], [8, 18], [8, 20], [9, 14], [9, 20], [9, 23], [10, 14], [10, 20], [11, 12], [11, 18], [11, 20], [11, 23], [12, 15], [12, 19], [12, 21], [12, 24], [13, 14], [13, 20], [13, 23], [14, 15], [14, 16], [14, 17], [14, 18], [14, 21], [14, 22], [14, 24], [15, 23], [16, 18], [16, 20], [16, 23], [17, 18], [17, 20], [18, 19], [18, 24], [19, 23], [20, 22], [20, 23], [21, 22], [21, 23], [22, 23], [23, 24]], "tanks": [{"capacity": 823, "impossibleCargos": [6, 9, 11, 12, 13, 14, 17], "neighbors": [6, 34, 33, 29, 31, 27, 18, 15, 11, 21, 20, 19, 32, 14, 1, 25, 2, 17, 5, 12, 30, 9, 26, 8, 7, 28]}, {"capacity": 813, "impossibleCargos": [1, 5, 8, 17], "neighbors": [25, 33, 5, 29, 24, 21, 20, 17, 13, 4, 10, 32, 34, 6, 11, 0, 14, 22, 28, 30, 19, 12, 15, 18, 9, 31, 3, 27]}, {"capacity": 837, "impossibleCargos": [5, 6, 9, 10, 15, 21, 22], "neighbors": [10, 28, 30, 7, 34, 25, 17, 6, 13, 32, 5, 3, 12, 16, 29, 26, 27, 0, 31, 21, 18, 4]}, {"capacity": 996, "impossibleCargos": [0, 3, 10, 13, 14, 20, 23, 24], "neighbors": [30, 14, 23, 21, 11, 7, 16, 26, 13, 31, 15, 10, 9, 34, 4, 25, 32, 12, 2, 27, 33, 24, 17, 18, 6, 1]}, {"capacity": 605, "impossibleCargos": [0, 7, 8, 9, 12, 15, 17], "neighbors": [20, 17, 34, 15, 13, 8, 9, 18, 14, 11, 3, 21, 25, 1, 23, 12, 27, 30, 10, 31, 33, 32, 16, 29, 22, 5, 24, 26, 6, 2]}, {"capacity": 731, "impossibleCargos": [1, 5, 10, 11, 23], "neighbors": [19, 21, 6, 31, 17, 27, 1, 8, 25, 26, 2, 7, 14, 12, 30, 13, 9, 0, 4, 20, 29, 22, 23]}, {"capacity": 974, "impossibleCargos": [4, 8, 17, 21], "neighbors": [10, 0, 5, 16, 17, 29, 34, 32, 2, 20, 12, 7, 28, 27, 23, 1, 33, 13, 11, 25, 9, 3, 24, 4, 8]}, {"capacity": 222, "impossibleCargos": [1, 5, 6, 14, 15, 21, 24], "neighbors": [20, 3, 23, 16, 29, 30, 9, 2, 13, 24, 14, 25, 19, 8, 6, 17, 21, 34, 22, 5, 10, 28, 26, 15, 27, 0, 18]}, {"capacity": 455, "impossibleCargos": [9, 18, 19], "neighbors": [18, 26, 4, 21, 29, 19, 9, 12, 5, 33, 30, 7, 15, 23, 24, 28, 25, 14, 32, 16, 13, 17, 0, 6]}, {"capacity": 352, "impossibleCargos": [2, 3, 4, 5, 8, 12, 13, 15, 18, 23], "neighbors": [17, 34, 11, 29, 24, 25, 10, 18, 21, 4, 22, 7, 8, 3, 31, 13, 28, 14, 30, 33, 16, 19, 23, 5, 6, 0, 1, 32]}, {"capacity": 391, "impossibleCargos": [4, 12, 14, 15], "neighbors": [6, 2, 26, 30, 11, 9, 23, 22, 34, 3, 16, 27, 20, 18, 1, 21, 12, 13, 4, 19, 14, 7, 17, 15, 28]}, {"capacity": 694, "impossibleCargos": [3, 4, 5, 8, 12, 17, 18, 19, 20, 22, 23], "neighbors": [9, 24, 10, 14, 18, 3, 4, 15, 29, 12, 0, 31, 1, 34, 33, 26, 6, 21, 20, 13, 17, 25, 19]}, {"capacity": 642, "impossibleCargos": [13, 21], "neighbors": [25, 33, 28, 34, 22, 23, 8, 13, 29, 31, 11, 6, 32, 10, 4, 3, 17, 15, 20, 2, 24, 5, 30, 27, 18, 1, 0, 14]}, {"capacity": 762, "impossibleCargos": [3, 6, 7, 14, 23], "neighbors": [23, 4, 30, 3, 22, 20, 12, 7, 2, 1, 15, 26, 9, 14, 16, 10, 17, 27, 34, 32, 5, 18, 28, 6, 8, 11, 25, 29]}, {"capacity": 389, "impossibleCargos": [0, 8, 11, 13, 23], "neighbors": [3, 15, 11, 32, 4, 34, 29, 7, 13, 9, 31, 25, 33, 5, 0, 8, 18, 10, 1, 24, 27, 16, 12, 26, 20]}, {"capacity": 326, "impossibleCargos": [0, 13, 15, 17, 23], "neighbors": [23, 22, 14, 4, 20, 17, 31, 3, 0, 11, 13, 19, 8, 30, 12, 28, 33, 25, 32, 24, 1, 18, 10, 7, 26, 16]}, {"capacity": 573, "impossibleCargos": [1, 4, 10, 13, 14, 24], "neighbors": [6, 19, 26, 31, 17, 3, 7, 30, 10, 29, 18, 21, 13, 27, 2, 9, 34, 4, 8, 22, 20, 14, 32, 15, 33]}, {"capacity": 900, "impossibleCargos": [3, 7, 8, 14, 22, 23], "neighbors": [9, 27, 24, 4, 6, 16, 5, 15, 26, 22, 18, 1, 31, 2, 7, 12, 13, 23, 3, 21, 34, 0, 10, 19, 32, 25, 8, 11]}, {"capacity": 219, "impossibleCargos": [10, 11, 14, 18], "neighbors": [8, 9, 11, 31, 29, 4, 0, 17, 26, 22, 16, 24, 32, 10, 27, 21, 19, 14, 25, 13, 12, 15, 3, 2, 1, 30, 7]}, {"capacity": 722, "impossibleCargos": [2, 7, 9, 13, 16, 24], "neighbors": [5, 20, 16, 27, 26, 34, 8, 32, 24, 15, 7, 22, 31, 30, 18, 0, 29, 10, 9, 25, 1, 17, 33, 21, 11]}, {"capacity": 672, "impossibleCargos": [6, 13, 19, 24], "neighbors": [4, 19, 31, 7, 15, 34, 22, 13, 29, 1, 10, 6, 0, 12, 28, 27, 11, 5, 25, 16, 21, 32, 14]}, {"capacity": 410, "impossibleCargos": [0, 5, 6, 7, 8, 10, 12, 19], "neighbors": [32, 26, 5, 29, 3, 9, 8, 31, 1, 4, 28, 27, 16, 10, 7, 0, 18, 24, 23, 17, 11, 33, 2, 20, 19]}, {"capacity": 966, "impossibleCargos": [0, 5, 8, 23], "neighbors": [24, 33, 15, 34, 9, 17, 13, 10, 20, 12, 18, 23, 32, 19, 28, 7, 27, 1, 29, 26, 4, 16, 30, 5]}, {"capacity": 982, "impossibleCargos": [5, 14, 17, 18, 23], "neighbors": [25, 15, 13, 24, 3, 27, 10, 7, 28, 34, 32, 12, 29, 4, 22, 26, 8, 17, 6, 21, 9, 5]}, {"capacity": 306, "impossibleCargos": [3, 6, 9, 17, 20, 22], "neighbors": [22, 23, 34, 17, 11, 9, 33, 1, 30, 18, 25, 7, 19, 26, 8, 21, 12, 3, 15, 14, 28, 29, 4, 6]}, {"capacity": 886, "impossibleCargos": [11, 15, 18, 22], "neighbors": [12, 23, 26, 1, 28, 9, 30, 2, 4, 3, 27, 24, 7, 5, 14, 8, 15, 0, 18, 19, 6, 34, 20, 17, 13, 11]}, {"capacity": 570, "impossibleCargos": [3, 4, 9, 12, 15, 22, 23], "neighbors": [25, 21, 10, 16, 8, 34, 30, 19, 27, 3, 17, 18, 33, 23, 5, 29, 13, 24, 11, 2, 7, 22, 31, 15, 4, 14, 0]}, {"capacity": 439, "impossibleCargos": [2, 4, 5, 10, 16, 20, 21], "neighbors": [17, 19, 23, 5, 26, 28, 0, 30, 10, 21, 25, 18, 4, 16, 3, 13, 6, 29, 22, 34, 20, 12, 2, 14, 7, 33, 1]}, {"capacity": 328, "impossibleCargos": [3, 12, 24], "neighbors": [25, 12, 30, 34, 2, 23, 27, 29, 21, 33, 22, 9, 6, 8, 15, 20, 1, 13, 7, 24, 32, 0, 10]}, {"capacity": 703, "impossibleCargos": [0, 1, 5, 7, 8, 9, 10, 13, 20], "neighbors": [21, 9, 6, 33, 0, 18, 7, 28, 8, 1, 20, 16, 12, 23, 14, 11, 26, 19, 27, 34, 2, 30, 24, 22, 31, 4, 5, 13]}, {"capacity": 832, "impossibleCargos": [12, 15, 19, 21], "neighbors": [3, 10, 25, 26, 34, 13, 28, 2, 7, 16, 27, 24, 33, 31, 8, 15, 19, 4, 9, 29, 5, 12, 1, 0, 32, 18, 22]}, {"capacity": 501, "impossibleCargos": [0, 1, 6, 13, 15, 17, 18], "neighbors": [5, 20, 16, 18, 0, 21, 15, 3, 17, 33, 9, 30, 12, 19, 11, 14, 4, 29, 2, 26, 1]}, {"capacity": 338, "impossibleCargos": [], "neighbors": [21, 14, 6, 23, 19, 34, 3, 22, 18, 2, 12, 33, 1, 0, 15, 13, 8, 4, 20, 17, 16, 30, 28, 9]}, {"capacity": 876, "impossibleCargos": [1, 2, 7, 10, 13, 14, 16], "neighbors": [22, 12, 0, 29, 1, 24, 31, 30, 8, 26, 28, 32, 34, 14, 15, 9, 3, 11, 6, 4, 21, 19, 27, 16]}, {"capacity": 580, "impossibleCargos": [4, 7, 14, 17, 21, 23, 24], "neighbors": [9, 24, 26, 0, 4, 22, 30, 19, 28, 6, 20, 12, 2, 10, 23, 3, 14, 32, 7, 33, 1, 29, 13, 11, 27, 16, 17, 25]}]}