{"volumes": [2350, 871, 458, 0, 0, 0, 0, 0, 722, 0, 691, 770, 265, 1555, 0, 432, 1373, 1057, 268, 0, 1627, 2550, 261, 1029, 427, 416, 469, 183, 0, 248], "conflicts": [[0, 2], [0, 3], [0, 5], [0, 6], [0, 9], [0, 14], [0, 19], [1, 6], [1, 7], [1, 8], [1, 11], [1, 12], [1, 19], [2, 6], [2, 14], [2, 25], [2, 29], [3, 6], [3, 13], [3, 15], [3, 17], [3, 20], [3, 29], [4, 10], [4, 11], [4, 15], [4, 16], [4, 18], [4, 25], [5, 9], [5, 14], [5, 15], [5, 18], [5, 24], [5, 26], [5, 27], [5, 28], [6, 7], [6, 21], [6, 25], [7, 13], [7, 18], [7, 22], [7, 29], [8, 12], [8, 14], [8, 22], [8, 29], [9, 11], [9, 16], [9, 18], [9, 21], [9, 22], [10, 12], [10, 20], [10, 23], [10, 28], [10, 29], [11, 24], [11, 27], [12, 17], [12, 18], [12, 20], [12, 22], [12, 29], [13, 14], [14, 24], [15, 19], [16, 22], [16, 24], [17, 18], [17, 22], [17, 24], [17, 26], [18, 19], [19, 24], [22, 24], [22, 27], [22, 28], [22, 29], [25, 27], [26, 28], [27, 28]], "tanks": [{"capacity": 898, "impossibleCargos": [0, 1, 3, 4, 5, 6, 7, 8, 9, 10, 11, 13, 14, 15, 16, 18, 20, 21, 22, 23, 24, 25, 26, 28, 29], "neighbors": [30, 11, 20, 32, 34, 3, 9, 22, 29]}, {"capacity": 491, "impossibleCargos": [2, 3, 4, 5, 6, 7, 8, 9, 10, 11, 13, 14, 16, 17, 18, 19, 20, 21, 24, 25, 26, 28, 29], "neighbors": [15, 24, 3, 19, 27, 8, 10, 12, 22, 23, 5, 28, 25]}, {"capacity": 618, "impossibleCargos": [0, 1, 3, 4, 6, 8, 9, 10, 11, 14, 15, 16, 17, 18, 22, 23, 24, 25, 26, 27, 28, 29], "neighbors": [24, 12, 30, 10, 23, 21, 17, 34]}, {"capacity": 417, "impossibleCargos": [0, 1, 3, 5, 6, 7, 8, 9, 11, 12, 13, 14, 15, 16, 19, 20, 22, 23, 24, 25, 27, 29], "neighbors": [11, 12, 14, 1, 28, 0, 18, 6, 34, 30, 36]}, {"capacity": 752, "impossibleCargos": [3, 4, 7, 9, 10, 11, 12, 13, 14, 15, 16, 18, 19, 20, 23, 24, 25, 26, 27, 28], "neighbors": [27, 12, 36, 17, 39, 19, 18, 34, 25, 7, 30]}, {"capacity": 503, "impossibleCargos": [1, 3, 5, 6, 7, 8, 10, 11, 12, 13, 16, 17, 22, 25, 28, 29], "neighbors": [34, 7, 1, 17, 11, 25]}, {"capacity": 699, "impossibleCargos": [0, 1, 2, 6, 8, 10, 13, 14, 15, 18, 19, 24, 25, 26, 27, 28, 29], "neighbors": [18, 37, 38, 10, 24, 17, 3, 13, 34, 15, 35]}, {"capacity": 704, "impossibleCargos": [1, 2, 3, 4, 5, 6, 7, 8, 11, 12, 13, 15, 17, 18, 20, 21, 22, 23, 24, 27, 29], "neighbors": [36, 33, 23, 5, 12, 4, 20, 13, 25]}, {"capacity": 722, "impossibleCargos": [0, 1, 2, 3, 4, 6, 7, 9, 11, 12, 13, 15, 17, 18, 19, 20, 22, 23, 24, 25, 26, 27, 28, 29], "neighbors": [28, 24, 1, 11, 21, 34, 29]}, {"capacity": 790, "impossibleCargos": [1, 2, 4, 6, 7, 8, 9, 12, 13, 14, 15, 16, 17, 18, 19, 20, 21, 22, 23, 24, 25, 27], "neighbors": [24, 19, 18, 27, 32, 0, 23, 30, 11, 28]}, {"capacity": 680, "impossibleCargos": [0, 2, 3, 4, 5, 6, 7, 8, 9, 11, 12, 13, 15, 16, 18, 19, 23, 24, 25, 26, 28, 29], "neighbors": [2, 17, 6, 36, 26, 1, 24, 32, 27]}, {"capacity": 859, "impossibleCargos": [1, 2, 3, 5, 6, 7, 9, 10, 11, 12, 13, 14, 15, 16, 17, 19, 20, 22, 24, 25, 27, 29], "neighbors": [3, 0, 25, 14, 17, 12, 8, 23, 9, 5, 33]}, {"capacity": 539, "impossibleCargos": [0, 1, 2, 3, 4, 5, 6, 7, 9, 10, 11, 12, 13, 14, 17, 18, 20, 21, 22, 23, 24, 25, 26, 28, 29], "neighbors": [2, 4, 3, 37, 20, 11, 1, 39, 7, 17, 30, 19, 36]}, {"capacity": 568, "impossibleCargos": [0, 1, 2, 3, 4, 5, 8, 9, 10, 11, 16, 17, 19, 20, 21, 22, 23, 24, 25, 27, 28, 29], "neighbors": [18, 22, 21, 38, 17, 29, 6, 19, 39, 7, 15, 23]}, {"capacity": 474, "impossibleCargos": [0, 1, 2, 4, 5, 6, 7, 8, 9, 10, 13, 15, 16, 17, 18, 19, 20, 22, 23, 25, 27], "neighbors": [15, 26, 3, 34, 18, 11, 32, 31, 36, 33]}, {"capacity": 274, "impossibleCargos": [0, 2, 3, 4, 5, 7, 8, 10, 12, 13, 16, 17, 18, 19, 20, 23, 25, 27, 29], "neighbors": [1, 14, 21, 32, 29, 39, 6, 13]}, {"capacity": 449, "impossibleCargos": [1, 2, 6, 9, 10, 11, 12, 13, 14, 16, 17, 18, 19, 20, 23, 24, 25, 26, 28], "neighbors": [21, 31, 24, 17, 39, 23, 30, 26]}, {"capacity": 998, "impossibleCargos": [1, 2, 3, 4, 5, 6, 7, 8, 9, 10, 11, 13, 14, 16, 17, 18, 19, 20, 24, 25, 26, 28], "neighbors": [4, 16, 10, 26, 11, 31, 13, 2, 39, 6, 19, 12, 24, 5, 28]}, {"capacity": 378, "impossibleCargos": [0, 1, 2, 3, 6, 7, 8, 9, 12, 13, 14, 15, 16, 17, 19, 21, 22, 24, 25, 26, 28, 29], "neighbors": [28, 6, 32, 13, 9, 14, 3, 4, 34, 24, 29]}, {"capacity": 442, "impossibleCargos": [0, 1, 2, 4, 5, 6, 9, 10, 11, 12, 13, 14, 16, 18, 19, 20, 22, 24, 25, 27], "neighbors": [9, 27, 20, 1, 21, 37, 4, 17, 13, 12]}, {"capacity": 816, "impossibleCargos": [0, 1, 3, 4, 9, 10, 11, 12, 13, 16, 19, 20, 21, 22, 23, 24, 25, 26, 27, 28, 29], "neighbors": [23, 0, 19, 12, 34, 7, 31]}, {"capacity": 523, "impossibleCargos": [0, 1, 2, 3, 5, 7, 8, 9, 10, 12, 13, 14, 15, 16, 17, 18, 19, 20, 21, 22, 23, 24, 26, 28, 29], "neighbors": [16, 24, 2, 13, 15, 19, 8, 33]}, {"capacity": 916, "impossibleCargos": [0, 1, 2, 3, 4, 6, 7, 8, 9, 10, 12, 13, 14, 15, 17, 18, 20, 21, 22, 25, 26, 27, 29], "neighbors": [13, 0, 37, 1, 27]}, {"capacity": 913, "impossibleCargos": [0, 2, 3, 4, 5, 6, 7, 8, 9, 10, 11, 12, 14, 17, 18, 19, 22, 24, 25, 26, 27, 28, 29], "neighbors": [20, 2, 35, 7, 26, 9, 1, 16, 11, 36, 29, 13, 30]}, {"capacity": 739, "impossibleCargos": [3, 4, 5, 6, 7, 8, 9, 10, 11, 12, 13, 14, 15, 16, 17, 18, 19, 20, 21, 23, 27, 28, 29], "neighbors": [34, 2, 16, 1, 9, 21, 8, 6, 31, 10, 25, 17, 18]}, {"capacity": 321, "impossibleCargos": [0, 1, 2, 3, 5, 6, 7, 8, 9, 10, 11, 13, 15, 17, 20, 21, 22, 23, 25, 29], "neighbors": [31, 11, 24, 4, 37, 1, 7, 5]}, {"capacity": 906, "impossibleCargos": [0, 2, 3, 4, 6, 8, 9, 10, 11, 12, 15, 16, 18, 19, 20, 23, 24, 25, 26, 27], "neighbors": [38, 14, 17, 10, 23, 29, 28, 16, 31, 33]}, {"capacity": 376, "impossibleCargos": [0, 1, 2, 3, 5, 6, 7, 8, 9, 11, 12, 13, 14, 15, 17, 18, 19, 20, 21, 22, 24, 25, 26, 27, 28, 29], "neighbors": [4, 19, 9, 1, 22, 10, 37, 31]}, {"capacity": 574, "impossibleCargos": [0, 1, 2, 3, 4, 5, 6, 8, 10, 11, 12, 15, 16, 18, 19, 20, 22, 23, 24, 25, 26, 27, 28, 29], "neighbors": [18, 8, 37, 3, 39, 26, 17, 1, 9]}, {"capacity": 992, "impossibleCargos": [3, 4, 6, 7, 8, 9, 10, 14, 15, 17, 18, 19, 20, 21, 22, 23, 24, 25, 26, 27, 28, 29], "neighbors": [30, 33, 13, 15, 26, 0, 8, 23, 18]}, {"capacity": 744, "impossibleCargos": [0, 1, 2, 3, 4, 5, 6, 7, 8, 9, 10, 11, 13, 14, 15, 16, 17, 19, 22, 23, 24, 25, 26, 27, 28, 29], "neighbors": [32, 0, 29, 2, 37, 33, 38, 16, 9, 12, 4, 3, 23]}, {"capacity": 260, "impossibleCargos": [0, 1, 2, 3, 6, 9, 10, 11, 12, 14, 15, 16, 17, 18, 19, 20, 21, 22, 23, 24, 25, 28, 29], "neighbors": [16, 25, 34, 17, 14, 24, 33, 27, 20, 26]}, {"capacity": 774, "impossibleCargos": [0, 1, 3, 4, 5, 6, 7, 8, 9, 10, 11, 12, 15, 17, 18, 19, 21, 24, 25, 26, 27, 28, 29], "neighbors": [30, 18, 35, 0, 9, 14, 15, 10, 38, 34]}, {"capacity": 548, "impossibleCargos": [0, 1, 2, 3, 4, 5, 6, 7, 8, 10, 11, 12, 13, 15, 16, 17, 19, 20, 21, 22, 24, 27], "neighbors": [7, 29, 39, 30, 36, 31, 14, 21, 26, 11]}, {"capacity": 700, "impossibleCargos": [0, 3, 4, 5, 6, 7, 9, 10, 11, 12, 14, 15, 16, 17, 18, 19, 20, 21, 22, 23, 24, 25, 26, 27, 28, 29], "neighbors": [24, 14, 5, 31, 0, 36, 8, 18, 4, 20, 6, 3, 2, 32]}, {"capacity": 384, "impossibleCargos": [0, 2, 3, 4, 5, 7, 8, 9, 10, 11, 12, 14, 16, 17, 18, 19, 20, 21, 24, 25, 26, 27, 28, 29], "neighbors": [37, 38, 32, 23, 36, 6]}, {"capacity": 202, "impossibleCargos": [0, 2, 3, 5, 6, 8, 9, 10, 11, 12, 14, 15, 17, 18, 20, 21, 23, 24, 26], "neighbors": [7, 4, 10, 35, 34, 33, 23, 14, 12, 37, 3]}, {"capacity": 620, "impossibleCargos": [0, 3, 4, 5, 10, 11, 12, 13, 14, 15, 16, 17, 18, 19, 20, 21, 22, 23, 24, 25, 26, 27, 28, 29], "neighbors": [30, 12, 6, 35, 28, 22, 19, 25, 27, 36]}, {"capacity": 378, "impossibleCargos": [0, 1, 2, 3, 5, 6, 7, 8, 9, 10, 11, 12, 13, 14, 15, 17, 19, 20, 21, 23, 24, 25, 26, 27, 28], "neighbors": [26, 35, 6, 13, 32, 30]}, {"capacity": 353, "impossibleCargos": [0, 1, 4, 5, 6, 10, 12, 14, 15, 16, 17, 18, 19, 22, 24, 27, 28], "neighbors": [16, 4, 12, 17, 33, 28, 13, 15]}]}